garcia2009/__init__.py
garcia2009/formalism.py
garcia2009/info.py
garcia2009/params.py
garcia2009/version.py
garcia2009/clean/readme.rst
garcia2009/clean/table5.csv
garcia2009/clean/table8.csv
garcia2009-1.2.0.dist-info/AUTHORS.rst
garcia2009-1.2.0.dist-info/LICENSE
garcia2009-1.2.0.dist-info/METADATA
garcia2009-1.2.0.dist-info/WHEEL
garcia2009-1.2.0.dist-info/top_level.txt
garcia2009-1.2.0.dist-info/RECORD
