Metadata-Version: 2.1
Name: garcia2009
Version: 1.2.0
Summary: Description of BRIN model from García de Cortázar-Atauri et al. 2009
Author-email: revesansparole <revesansparole@gmail.com>
Maintainer-email: revesansparole <revesansparole@gmail.com>, Jerome Chopard <revesansparole@gmail.com>
License: cc_by_nc
Project-URL: repository, https://gitlab.com/b326/garcia2009
Project-URL: pip, https://pypi.org/project/garcia2009/1.2.0/
Project-URL: conda, https://anaconda.org/revesansparole/garcia2009
Project-URL: doc, https://b326.gitlab.io/garcia2009/
Project-URL: pypi, https://badge.fury.io/py/garcia2009
Classifier: Development Status :: 2 - Pre-Alpha
Classifier: Intended Audience :: Developers
Classifier: License :: OSI Approved :: BSD License
Classifier: Natural Language :: English
Classifier: Programming Language :: Python
Classifier: Programming Language :: Python :: 3
Classifier: Programming Language :: Python :: 3 :: Only
Classifier: Programming Language :: Python :: 3.9
Requires-Python: >=3.9
License-File: LICENSE
License-File: AUTHORS.rst
Provides-Extra: doc
Requires-Dist: sphinx ; extra == 'doc'
Requires-Dist: sphinx-gallery ; extra == 'doc'
Requires-Dist: sphinx-rtd-theme ; extra == 'doc'
Provides-Extra: dvlpt
Requires-Dist: twine ; extra == 'dvlpt'
Provides-Extra: example
Requires-Dist: matplotlib ; extra == 'example'
Requires-Dist: pandas ; extra == 'example'
Provides-Extra: test
Requires-Dist: coverage ; extra == 'test'
Requires-Dist: pytest ; extra == 'test'
Requires-Dist: pytest-cov ; extra == 'test'
Requires-Dist: pytest-mock ; extra == 'test'
